winscppasswdextractor/WinSCPPasswdExtractor.py
winscppasswdextractor-1.2.0.dist-info/entry_points.txt
winscppasswdextractor-1.2.0.dist-info/LICENCE
winscppasswdextractor-1.2.0.dist-info/METADATA
winscppasswdextractor-1.2.0.dist-info/WHEEL
winscppasswdextractor-1.2.0.dist-info/RECORD
