Metadata-Version: 2.3
Name: WinSCPPasswdExtractor
Version: 1.2.0
Summary: Extract WinSCP Credentials from any Windows System, winscp config file or recovered user registry hive file
License: MIT
Author: Alexander Neff
Author-email: alex99.neff@gmx.de
Requires-Python: >=3.7,<4.0
Classifier: License :: OSI Approved :: MIT License
Classifier: Programming Language :: Python :: 3
Classifier: Programming Language :: Python :: 3.7
Classifier: Programming Language :: Python :: 3.8
Classifier: Programming Language :: Python :: 3.9
Classifier: Programming Language :: Python :: 3.10
Classifier: Programming Language :: Python :: 3.11
Classifier: Programming Language :: Python :: 3.12
Classifier: Programming Language :: Python :: 3.13
Requires-Dist: python-registry (>=1.3.1,<2.0.0)
Project-URL: Homepage, https://github.com/NeffIsBack/WinSCPPasswdExtractor
Project-URL: Repository, https://github.com/NeffIsBack/WinSCPPasswdExtractor
